html_speak/__init__.py
html_speak/server.py
html_speak/util.py
html_speak-0.1.1.dist-info/WHEEL
html_speak-0.1.1.dist-info/METADATA
html_speak-0.1.1.dist-info/RECORD
