Metadata-Version: 2.1
Name: html-speak
Version: 0.1.1
Summary: HTML TTS server for Chinese/Japanese and Jupyter Notebook
Home-page: https://github.com/patarapolw/html-speak
License: MIT
Keywords: tts
Author: Pacharapol Withayasakpunt
Author-email: patarapolw@gmail.com
Classifier: License :: OSI Approved :: MIT License
Classifier: Programming Language :: Python :: 2
Classifier: Programming Language :: Python :: 2.7
Classifier: Programming Language :: Python :: 3
Classifier: Programming Language :: Python :: 3.4
Classifier: Programming Language :: Python :: 3.5
Classifier: Programming Language :: Python :: 3.6
Classifier: Programming Language :: Python :: 3.7
Requires-Dist: falcon (>=1.4,<2.0)
Requires-Dist: gunicorn (>=19.9,<20.0)
Requires-Dist: regex (==2018.02.21)
Requires-Dist: ttslib (>=0.1.0,<0.2.0)
